pykeyval/__init__.py
pykeyval/dict_keyval.py
pykeyval/file_keyval.py
pykeyval/interface.py
pykeyval/pykeyval.py
pykeyval/redis_keyval.py
pykeyval/serializers.py
pykeyval/snow_keyval.py
pykeyval/sqlite_keyval.py
pykeyval-0.0.2.dist-info/METADATA
pykeyval-0.0.2.dist-info/WHEEL
pykeyval-0.0.2.dist-info/top_level.txt
pykeyval-0.0.2.dist-info/RECORD
