Metadata-Version: 2.1
Name: pykeyval
Version: 0.0.2
Summary: PyKeyVal is a key-value store that you can pack in a bag and take with you.
Home-page: UNKNOWN
Author: tchoedak@gmail.com
License: UNKNOWN
Platform: UNKNOWN
Requires-Dist: redis (>=3.3.11)
Requires-Dist: SQLAlchemy (>=1.3.3)
Requires-Dist: snowflake-sqlalchemy (>=1.1.16)
